taskq/__init__.py
taskq/__main__.py
taskq/abort-handler.py
taskq/models.py
taskq/resources.py
taskq/settings.py
taskq/task-handler.py
taskq/taskq-bot.py
taskq/utils.py
task_q-1.1.4.dist-info/METADATA
task_q-1.1.4.dist-info/WHEEL
task_q-1.1.4.dist-info/dependency_links.txt
task_q-1.1.4.dist-info/entry_points.txt
task_q-1.1.4.dist-info/top_level.txt
task_q-1.1.4.dist-info/RECORD
