Metadata-Version: 2.1
Name: task-q
Version: 1.1.4
Summary: A simple commandline app that implements a task queue
Home-page: UNKNOWN
Author: Rodrigo Cunha
Author-email: rodra.xyz@gmail.com
License: MIT
Platform: UNKNOWN
Classifier: License :: OSI Approved :: MIT License
Classifier: Programming Language :: Python :: 3.8
Requires-Python: >=3.8
Requires-Dist: peewee (==3.14.0)
Requires-Dist: tabulate (==0.8.7)
Requires-Dist: schedule (==0.6.0)
Requires-Dist: click (==7.1.2)
Requires-Dist: twine (==3.3.0)
